<?xml version="1.0" encoding="utf-8"?>
<!DOCTYPE hibernate-mapping PUBLIC "-//Hibernate/Hibernate Mapping DTD 3.0//EN"
"http://hibernate.sourceforge.net/hibernate-mapping-3.0.dtd">
<!-- 
    Mapping file autogenerated by MyEclipse Persistence Tools
-->
<hibernate-mapping>
    <class name="com.music.model.Singer" table="singer" catalog="music">
        <id name="singerid" type="java.lang.Integer">
            <column name="singerid" />
            <generator class="increment"></generator>
        </id>
        <property name="singername" type="java.lang.String">
            <column name="singername" length="40" not-null="true" />
        </property>
        <property name="introduction" type="java.lang.String">
            <column name="introduction" length="100" />
        </property>
        <property name="singerfilepath" type="java.lang.String">
            <column name="singerfilepath" length="80" />
        </property>
        <set name="albums" inverse="true">
            <key>
                <column name="singer" not-null="true" />
            </key>
            <one-to-many class="com.music.model.Album" />
        </set>
        <set name="songs" inverse="true">
            <key>
                <column name="singer" />
            </key>
            <one-to-many class="com.music.model.Song" />
        </set>
        <set name="songs_1" inverse="true">
            <key>
                <column name="singer" />
            </key>
            <one-to-many class="com.music.model.Song" />
        </set>
    </class>
</hibernate-mapping>
